nebula/__init__.py
nebula/nebula.py
nebula/nebula_genetic.py
nebula/nebula_multimodal.py
nebula/nebula_search.py
nebula_loss-0.4.1.dist-info/LICENSE
nebula_loss-0.4.1.dist-info/METADATA
nebula_loss-0.4.1.dist-info/WHEEL
nebula_loss-0.4.1.dist-info/top_level.txt
nebula_loss-0.4.1.dist-info/RECORD
